kaminpar/__init__.py
kaminpar/__init__.pyi
kaminpar/kaminpar_python.cpython-312-aarch64-linux-gnu.so
kaminpar/py.typed
kaminpar.libs/libtbb-0da301d2.so.12.16
kaminpar.libs/libtbbmalloc-fe10b3f8.so.2.16
kaminpar-3.7.0.dist-info/METADATA
kaminpar-3.7.0.dist-info/WHEEL
kaminpar-3.7.0.dist-info/RECORD
