Metadata-Version: 2.1
Name: kaminpar
Version: 3.7.0
Summary: Python Bindings for KaMinPar
Keywords: KaMinPar,Graph Partitioning
Author-Email: Daniel Seemaier <daniel.seemaier@kit.edu>
Maintainer-Email: Daniel Salwasser <daniel.salwasser@outlook.com>
Classifier: Development Status :: 5 - Production/Stable
Classifier: Topic :: Scientific/Engineering
Classifier: Topic :: Software Development :: Libraries
Classifier: Topic :: Software Development :: Libraries :: Python Modules
Classifier: Intended Audience :: Developers
Classifier: Intended Audience :: Science/Research
Classifier: Programming Language :: Python :: 3 :: Only
Classifier: Programming Language :: Python :: 3.9
Classifier: Programming Language :: Python :: 3.10
Classifier: Programming Language :: Python :: 3.11
Classifier: Programming Language :: Python :: 3.12
Classifier: Programming Language :: Python :: 3.13
Classifier: Programming Language :: C++
Classifier: Operating System :: POSIX :: Linux
Classifier: Operating System :: MacOS
Classifier: License :: OSI Approved :: MIT License
Project-URL: Repository, https://github.com/KaHIP/KaMinPar.git
Project-URL: Issues, https://github.com/KaHIP/KaMinPar/issues
Requires-Python: >=3.9
